MANIFEST.in
setup.py
rampage/__init__.py
rampage/__main__.py
rampage/format.py
rampage/queuer.py
rampage/ramps.py
rampage/server.py
rampage/zmq_server.py
rampage.egg-info/PKG-INFO
rampage.egg-info/SOURCES.txt
rampage.egg-info/dependency_links.txt
rampage.egg-info/not-zip-safe
rampage.egg-info/requires.txt
rampage.egg-info/top_level.txt
rampage/daq/__init__.py
rampage/daq/daq.py
rampage/daq/dds_server.py
rampage/daq/gpib.py
rampage/ui/MainWindow.ui
rampage/ui/Ramp1DScan.ui
rampage/ui/RampQueuer.ui
rampage/widgets/ChannelWidgets.py
rampage/widgets/CommonWidgets.py
rampage/widgets/DictEditor.py
rampage/widgets/KeyFrameWidgets.py
rampage/widgets/MainWindow.py
rampage/widgets/RampEditor.py
rampage/widgets/RampViewer.py
rampage/widgets/__init__.py