Metadata-Version: 1.1
Name: rampage
Version: 0.1.1
Summary: An arbitrary waveform builder and a control system for ultra-cold atom and ion trap experiments
Home-page: http://github.com/shreyaspotnis/rampage
Author: Shreyas Potnis
Author-email: shreyaspotnis@gmail.com
License: MIT
Platform: UNKNOWN
Classifier: Development Status :: 3 - Alpha
Classifier: Environment :: X11 Applications :: Qt
Classifier: Intended Audience :: Science/Research
Classifier: License :: OSI Approved :: MIT License
Classifier: Operating System :: OS Independent
Classifier: Programming Language :: Python :: 2.7
Classifier: Topic :: Multimedia :: Graphics :: Viewers
Classifier: Topic :: Scientific/Engineering :: Physics
Classifier: Topic :: Scientific/Engineering :: Visualization
